README.txt
setup.py
jiupin_utils/__init__.py
jiupin_utils.egg-info/PKG-INFO
jiupin_utils.egg-info/SOURCES.txt
jiupin_utils.egg-info/dependency_links.txt
jiupin_utils.egg-info/top_level.txt
jiupin_utils.egg-info/zip-safe
jiupin_utils/cache/__init__.py
jiupin_utils/cache/cache_v1.1.2.py
jiupin_utils/cache/cache_v1.py
jiupin_utils/cache/cache_v1_2.py
jiupin_utils/cmd_parser/__init__.py
jiupin_utils/cmd_parser/cmd_parser_v1.py
jiupin_utils/file_helper/__init__.py
jiupin_utils/file_helper/file_helper_v1.py
jiupin_utils/folder_helper/__init__.py
jiupin_utils/folder_helper/folder_helper_v1.py
jiupin_utils/mongo_db_helper/__init__.py
jiupin_utils/mongo_db_helper/mongo_db_helper_v1.py
jiupin_utils/mysql_db_helper/__init__.py
jiupin_utils/mysql_db_helper/mysql_db_helper_v1.py
jiupin_utils/oss_client/__init__.py
jiupin_utils/oss_client/oss_client_v1.py
jiupin_utils/return_result/__init__.py
jiupin_utils/return_result/return_result_v1.py
jiupin_utils/sqlite_db_helper/__init__.py
jiupin_utils/sqlite_db_helper/sqlite_db_helper_v1.py
jiupin_utils/time_helper/__init__.py
jiupin_utils/time_helper/time_helper_v1.py
jiupin_utils/val/__init__.py
jiupin_utils/val/vali_input_v1.py
jiupin_utils/val/vali_rule_chker_v1.py
jiupin_utils/val/vali_rule_info_v1.py
jiupin_utils/val/vali_rule_info_v2.py