Metadata-Version: 1.1
Name: jiupin-utils
Version: 1.0.25
Summary: this is a test package for packing python liberaries tutorial.
Home-page: http://www.9pin.cn/
Author: jiupin_utils
Author-email: 2055755366@qq.com
License: MIT
Keywords: test python package
Platform: UNKNOWN
Classifier: License :: OSI Approved :: MIT License
Classifier: Programming Language :: Python
Classifier: Intended Audience :: Developers
Classifier: Operating System :: OS Independent
